himpunan/Himpunan.py
himpunan/__init__.py
vakearyl-0.1.dist-info/METADATA
vakearyl-0.1.dist-info/WHEEL
vakearyl-0.1.dist-info/top_level.txt
vakearyl-0.1.dist-info/RECORD
