Metadata-Version: 2.4
Name: VaKeaRyl
Version: 0.1
Summary: Implementasi konsep himpunan menggunakan Python list dan magic methods.
Author: VaKeaRyl
License: MIT
Requires-Python: >=3.7
Dynamic: author
Dynamic: license
Dynamic: requires-python
Dynamic: summary
